xffunk/__init__.py
xffunk/tools.py
xffunk/xffn.py
xffunk/指纹浏览器.py
xffunk/接码.py
xffunk/请求.py
xffunk/DP浏览器/DP.py
xffunk/DP浏览器/FingerPrint.py
xffunk/DP浏览器/__init__.py
xffunk/DP浏览器/切换代理.js
xffunk/DP浏览器/Porxy/1.html
xffunk/DP浏览器/Porxy/__init__.py
xffunk/DP浏览器/Porxy/background.js
xffunk/DP浏览器/Porxy/manifest.json
xf_xf-0.0.7.dist-info/METADATA
xf_xf-0.0.7.dist-info/WHEEL
xf_xf-0.0.7.dist-info/top_level.txt
xf_xf-0.0.7.dist-info/RECORD
